README.md
setup.py
mttts/__init__.py
mttts/mttts.py
mttts.egg-info/PKG-INFO
mttts.egg-info/SOURCES.txt
mttts.egg-info/dependency_links.txt
mttts.egg-info/requires.txt
mttts.egg-info/top_level.txt