Metadata-Version: 2.1
Name: mttts
Version: 0.0.1
Summary: 语音服务SDK
Home-page: https://dev.sankuai.com/code/repo-detail/~ZHANGZHANG05/speech-sdk/file/list
Author: zhangzhang
Author-email: zhangzhang05@sankuai.com
License: MIT
Platform: UNKNOWN
Classifier: Programming Language :: Python :: 3
Classifier: License :: OSI Approved :: MIT License
Classifier: Operating System :: OS Independent
Requires-Python: >=3.6
